{"trial_id": "0023", "hyperparameters": {"space": [{"class_name": "Choice", "config": {"name": "activation", "default": "relu", "conditions": [], "values": ["relu", "tanh"], "ordered": false}}, {"class_name": "Int", "config": {"name": "layer1", "default": null, "conditions": [], "min_value": 100, "max_value": 1000, "step": 50, "sampling": "linear"}}, {"class_name": "Int", "config": {"name": "layer2", "default": null, "conditions": [], "min_value": 100, "max_value": 1000, "step": 50, "sampling": "linear"}}, {"class_name": "Choice", "config": {"name": "learning_rate", "default": 0.001, "conditions": [], "values": [0.001, 0.0005, 0.00025, 0.0001], "ordered": true}}, {"class_name": "Choice", "config": {"name": "optimizer", "default": "adam", "conditions": [], "values": ["adam", "nadam", "sgd", "rmsprop"], "ordered": false}}], "values": {"activation": "relu", "layer1": 200, "layer2": 350, "learning_rate": 0.001, "optimizer": "rmsprop", "tuner/epochs": 5, "tuner/initial_epoch": 0, "tuner/bracket": 1, "tuner/round": 0}}, "metrics": {"metrics": {"loss": {"direction": "min", "observations": [{"value": [0.33581313490867615], "step": 4}]}, "accuracy": {"direction": "max", "observations": [{"value": [0.8809999823570251], "step": 4}]}, "val_loss": {"direction": "min", "observations": [{"value": [0.4072597622871399], "step": 4}]}, "val_accuracy": {"direction": "max", "observations": [{"value": [0.8768333196640015], "step": 4}]}}}, "score": 0.8768333196640015, "best_step": 4, "status": "COMPLETED", "message": null}